{"type":"Topology","arcs":[[[1710,374],[-71,5],[-23,-30],[-139,-15],[-110,13],[-73,-22],[-139,-11],[-75,-17],[-101,26],[-68,-3],[-25,-16],[-49,-75],[-6,-63],[-32,-14],[-3,-44],[-68,-32],[-19,-56],[-36,-20],[-300,37],[-1,80],[41,243],[-413,51],[32,163],[34,195],[1,37],[50,-32],[42,10],[41,-18],[210,-33],[100,-7],[37,13],[64,-34],[169,0],[41,-38],[57,-23],[38,235],[56,-17],[224,-26],[63,53],[20,113],[281,-36],[41,-26],[157,74],[21,82],[20,21],[-31,-189],[-47,-244],[-11,-310]]],"transform":{"scale":[0.00008829461798063473,0.00008449000743028445],"translate":[145.13632937325715,-37.86515593577231]},"objects":{"auspol-maps-2016-p100-alldivisions":{"type":"GeometryCollection","geometries":[{"arcs":[[0]],"type":"Polygon","properties":{"Elect_div":"Deakin","State":"VIC","Numccds":240,"Actual":0,"Projected":0,"Total_Population":0,"Australians_Over_18":0,"Area_SqKm":69.8002859,"Sortname":"Deakin"}}]}}}