{"type":"Topology","arcs":[[[777,343],[-46,-147],[20,-62],[-102,15],[-108,71],[-149,50],[-22,-76],[-52,-60],[32,-42],[-18,-90],[-58,-2],[-101,85],[-76,4],[-20,96],[-77,11],[25,219],[73,85],[88,-100],[-3,192],[62,82],[69,6],[16,54],[104,11],[97,-37],[-42,-93],[21,-86],[100,-15],[45,-83],[-24,-56],[146,-32]]],"transform":{"scale":[0.00021914057390217643,0.00021140987607543916],"translate":[152.85487792873977,-27.685677658219845]},"objects":{"auspol-maps-2016-p100-alldivisions":{"type":"GeometryCollection","geometries":[{"arcs":[[0]],"type":"Polygon","properties":{"Elect_div":"Oxley","State":"QLD","Numccds":193,"Actual":0,"Projected":0,"Total_Population":0,"Australians_Over_18":0,"Area_SqKm":155.3490122750287,"Sortname":"OXLEY"}}]}}}